pysetl/__init__.py
pysetl/py.typed
pysetl/config/__init__.py
pysetl/config/aws_credentials.py
pysetl/config/config.py
pysetl/config/csv_config.py
pysetl/config/file_config.py
pysetl/config/json_config.py
pysetl/config/parquet_config.py
pysetl/enums/__init__.py
pysetl/enums/spark_encodings.py
pysetl/enums/spark_savemodes.py
pysetl/enums/storage.py
pysetl/storage/__init__.py
pysetl/storage/connector/__init__.py
pysetl/storage/connector/base_connector.py
pysetl/storage/connector/connector.py
pysetl/storage/connector/connector_builder.py
pysetl/storage/connector/csv_connector.py
pysetl/storage/connector/file_connector.py
pysetl/storage/connector/json_connector.py
pysetl/storage/connector/parquet_connector.py
pysetl/storage/repository/__init__.py
pysetl/storage/repository/base_repository.py
pysetl/storage/repository/sparkrepository.py
pysetl/storage/repository/sparkrepository_builder.py
pysetl/utils/__init__.py
pysetl/utils/benchmark_modifier.py
pysetl/utils/benchmark_result.py
pysetl/utils/builder.py
pysetl/utils/get_signature.py
pysetl/utils/pretty.py
pysetl/utils/exceptions/__init__.py
pysetl/utils/mixins/__init__.py
pysetl/utils/mixins/can_create.py
pysetl/utils/mixins/can_delete.py
pysetl/utils/mixins/can_drop.py
pysetl/utils/mixins/can_partition.py
pysetl/utils/mixins/can_update.py
pysetl/utils/mixins/can_wait.py
pysetl/utils/mixins/has_benchmark.py
pysetl/utils/mixins/has_diagram.py
pysetl/utils/mixins/has_logger.py
pysetl/utils/mixins/has_reader.py
pysetl/utils/mixins/has_registry.py
pysetl/utils/mixins/has_spark_session.py
pysetl/utils/mixins/has_writer.py
pysetl/utils/mixins/is_configurable.py
pysetl/utils/mixins/is_identifiable.py
pysetl/utils/mixins/is_writable.py
pysetl/workflow/__init__.py
pysetl/workflow/dag.py
pysetl/workflow/deliverable.py
pysetl/workflow/delivery.py
pysetl/workflow/delivery_type.py
pysetl/workflow/dispatcher.py
pysetl/workflow/expected_deliverable.py
pysetl/workflow/external.py
pysetl/workflow/factory.py
pysetl/workflow/flow.py
pysetl-1.2.1.dist-info/METADATA
pysetl-1.2.1.dist-info/WHEEL
pysetl-1.2.1.dist-info/licenses/LICENSE
pysetl-1.2.1.dist-info/RECORD
