Metadata-Version: 2.4
Name: pysetl
Version: 1.2.1
Summary: A PySpark ETL Framework
Project-URL: Home, https://github.com/JhossePaul/pysetl
Project-URL: Source, https://github.com/JhossePaul/pysetl
Author-email: Jhosse Paul Marquez Ruiz <jpaul.marquez.ruiz@gmail.com>
License: Apache-2.0
License-File: LICENSE
Keywords: analytics,automation,big data,configuration,data analysis,data engineering,data pipeline,data processing,data science,etl,framework,pipeline,pyspark,python,spark,type-safe,workflow
Classifier: Development Status :: 5 - Production/Stable
Classifier: Framework :: MkDocs
Classifier: Framework :: Pytest
Classifier: Intended Audience :: Developers
Classifier: Intended Audience :: Information Technology
Classifier: Intended Audience :: Science/Research
Classifier: License :: OSI Approved :: Apache Software License
Classifier: Natural Language :: English
Classifier: Operating System :: OS Independent
Classifier: Programming Language :: Python
Classifier: Programming Language :: Python :: 3
Classifier: Programming Language :: Python :: 3.9
Classifier: Programming Language :: Python :: 3.10
Classifier: Programming Language :: Python :: 3.11
Classifier: Programming Language :: Python :: 3.12
Classifier: Topic :: Database
Classifier: Topic :: Scientific/Engineering :: Information Analysis
Classifier: Topic :: Software Development :: Libraries
Classifier: Topic :: Software Development :: Libraries :: Application Frameworks
Classifier: Topic :: Software Development :: Libraries :: Python Modules
Classifier: Topic :: Utilities
Classifier: Typing :: Typed
Requires-Python: <3.14,>=3.9
Requires-Dist: pyarrow<21.0.0,>=15.0.0
Requires-Dist: pydantic<3.0.0,>=2.4.2
Requires-Dist: typedspark<2.0.0,>=1.5.3
Requires-Dist: typing-extensions<5.0.0,>=4.13.0
Provides-Extra: pyspark
Requires-Dist: pyspark[sql]<4.0.0,>=3.4; extra == 'pyspark'
